Metadata-Version: 2.1
Name: eatb
Version: 0.2.9
Summary: A suite of tools for the creation of information packages for archival purposes.
Home-page: https://www.e-ark-foundation.eu/e-ark-software-eatb
Author: E-ARK Foundation
Author-email: admin@e-ark-foundation.eu
License: MIT
Classifier: Intended Audience :: Developers
Classifier: License :: OSI Approved :: MIT License
Classifier: Programming Language :: Python :: 3
Classifier: Programming Language :: Python :: 3.5
Classifier: Programming Language :: Python :: 3.6
Classifier: Programming Language :: Python :: 3.7
Classifier: Programming Language :: Python :: 3.8
Classifier: Programming Language :: Python :: 3.9
Classifier: Programming Language :: Python :: 3.10
Classifier: Topic :: System :: Archiving
License-File: LICENSE
Requires-Dist: lxml
Requires-Dist: pytz
Requires-Dist: Pairtree
Requires-Dist: importlib_resources
Requires-Dist: opf-fido==1.6.1
Requires-Dist: eark-validator==1.1.1
Requires-Dist: urllib3==2.2.1
